instaffo_sklearn/__init__.py
instaffo_sklearn/preparation.py
instaffo_scikit_learn-0.2.2.dist-info/LICENSE
instaffo_scikit_learn-0.2.2.dist-info/WHEEL
instaffo_scikit_learn-0.2.2.dist-info/METADATA
instaffo_scikit_learn-0.2.2.dist-info/RECORD
