Metadata-Version: 2.1
Name: instaffo-scikit-learn
Version: 0.2.2
Summary: This project contains custom scikit-learn estimators that we use.
Home-page: https://instaffo.com
License: MIT
Keywords: scikit-learn,instaffo
Author: Instaffo GmbH
Author-email: info@instaffo.de
Requires-Python: >=3.6,<4.0
Classifier: License :: OSI Approved :: MIT License
Classifier: Programming Language :: Python :: 3
Classifier: Programming Language :: Python :: 3.6
Classifier: Programming Language :: Python :: 3.7
Requires-Dist: joblib (>=0.13,<0.14)
Requires-Dist: numpy (>=1.16,<2.0)
Requires-Dist: pandas (>=0.25,<0.26)
Requires-Dist: scikit-learn (>=0.21,<0.22)
Requires-Dist: scipy (>=1.3,<2.0)
Project-URL: Repository, https://gitlab.com/InstaffoOpenSource/DataScience/instaffo-scikit-learn
